{
  "tiles": [
    {
      "sprite": {
        "name": "vertical_brick",
        "filename": "newlizardsprite.png",
        "location": [0, 112],
        "size": [16, 16],
        "scale": 4,
        "number_of_frames": 1,
        "dt_per_frame": -1
      },
      "blocking": true,
      "event_name": ""
    },
    {
      "sprite": {
        "name": "horizontal_brick",
        "filename": "newlizardsprite.png",
        "location": [16, 112],
        "size": [16, 16],
        "scale": 4,
        "number_of_frames": 1,
        "dt_per_frame": -1
      },
      "blocking": true,
      "event_name": ""
    },
    {
      "sprite": {
        "name": "btm_right_brick",
        "filename": "newlizardsprite.png",
        "location": [32, 112],
        "size": [16, 16],
        "scale": 4,
        "number_of_frames": 1,
        "dt_per_frame": -1
      },
      "blocking": true,
      "event_name": ""
    },
    {
      "sprite": {
        "name": "btm_left_brick",
        "filename": "newlizardsprite.png",
        "location": [48, 112],
        "size": [16, 16],
        "scale": 4,
        "number_of_frames": 1,
        "dt_per_frame": -1
      },
      "blocking": true,
      "event_name": ""
    },
    {
      "sprite": {
        "name": "top_right_brick",
        "filename": "newlizardsprite.png",
        "location": [64, 112],
        "size": [16, 16],
        "scale": 4,
        "number_of_frames": 1,
        "dt_per_frame": -1
      },
      "blocking": true,
      "event_name": ""
    },
    {
      "sprite": {
        "name": "top_left_brick",
        "filename": "newlizardsprite.png",
        "location": [80, 112],
        "size": [16, 16],
        "scale": 4,
        "number_of_frames": 1,
        "dt_per_frame": -1
      },
      "blocking": true,
      "event_name": ""
    },
    {
      "sprite": {
        "name": "top_vert_end",
        "filename": "newlizardsprite.png",
        "location": [96, 112],
        "size": [16, 16],
        "scale": 4,
        "number_of_frames": 1,
        "dt_per_frame": -1
      },
      "blocking": true,
      "event_name": ""
    },
    {
      "sprite": {
        "name": "btm_vert_end",
        "filename": "newlizardsprite.png",
        "location": [112, 112],
        "size": [16, 16],
        "scale": 4,
        "number_of_frames": 1,
        "dt_per_frame": -1
      },
      "blocking": true,
      "event_name": ""
    },
    {
      "sprite": {
        "name": "horizontal_left_end",
        "filename": "newlizardsprite.png",
        "location": [128, 112],
        "size": [16, 16],
        "scale": 4,
        "number_of_frames": 1,
        "dt_per_frame": -1
      },
      "blocking": true,
      "event_name": ""
    },
    {
      "sprite": {
        "name": "horizontal_right_end",
        "filename": "newlizardsprite.png",
        "location": [144, 112],
        "size": [16, 16],
        "scale": 4,
        "number_of_frames": 1,
        "dt_per_frame": -1
      },
      "blocking": true,
      "event_name": ""
    },
    {
      "sprite": {
        "name": "next_level",
        "filename": "newlizardsprite.png",
        "location": [0, 128],
        "size": [16, 16],
        "scale": 4,
        "number_of_frames": 1,
        "dt_per_frame": -1
      },
      "blocking": true,
      "event_name": "next_level"
    },
    {
      "sprite": {
        "name": "previous_level",
        "filename": "newlizardsprite.png",
        "location": [16, 128],
        "size": [16, 16],
        "scale": 4,
        "number_of_frames": 1,
        "dt_per_frame": -1
      },
      "blocking": true,
      "event_name": "previous_level"
    },
    {
      "sprite": {
        "name": "treasure_room",
        "filename": "newlizardsprite.png",
        "location": [32, 128],
        "size": [16, 16],
        "scale": 4,
        "number_of_frames": 1,
        "dt_per_frame": -1
      },
      "blocking": false,
      "event_name": "treasure_room"
    },
    {
      "sprite": {
        "name": "out_treasure_room",
        "filename": "newlizardsprite.png",
        "location": [32, 144],
        "size": [16, 16],
        "scale": 4,
        "number_of_frames": 1,
        "dt_per_frame": -1
      },
      "blocking": true,
      "event_name": "treasure_room_out"
    },
    {
      "sprite": {
        "name": "spike",
        "filename": "newlizardsprite.png",
        "location": [48, 128],
        "size": [16, 16],
        "scale": 4,
        "number_of_frames": 1,
        "dt_per_frame": -1
      },
      "blocking": false,
      "event_name": "spiked"
    },
    {
      "sprite": {
        "name": "sand",
        "filename": "newlizardsprite.png",
        "location": [64, 128],
        "size": [16, 16],
        "scale": 4,
        "number_of_frames": 1,
        "dt_per_frame": -1
      },
      "blocking": false,
      "event_name": ""
    },
    {
      "sprite": {
        "name": "blocking-sand",
        "filename": "newlizardsprite.png",
        "location": [64, 128],
        "size": [16, 16],
        "scale": 4,
        "number_of_frames": 1,
        "dt_per_frame": -1
      },
      "blocking": true,
      "event_name": ""
    },
    {
      "sprite": {
        "name": "gravel",
        "filename": "newlizardsprite.png",
        "location": [80, 128],
        "size": [16, 16],
        "scale": 4,
        "number_of_frames": 1,
        "dt_per_frame": -1
      },
      "blocking": false,
      "event_name": ""
    },
    {
      "sprite": {
        "name": "blocking-gravel",
        "filename": "newlizardsprite.png",
        "location": [80, 128],
        "size": [16, 16],
        "scale": 4,
        "number_of_frames": 1,
        "dt_per_frame": -1
      },
      "blocking": true,
      "event_name": ""
    },
    {
      "sprite": {
        "name": "sky",
        "filename": "newlizardsprite.png",
        "location": [96, 128],
        "size": [16, 16],
        "scale": 4,
        "number_of_frames": 1,
        "dt_per_frame": -1
      },
      "blocking": false,
      "event_name": ""
    },
    {
      "sprite": {
        "name": "blocking-sky",
        "filename": "newlizardsprite.png",
        "location": [96, 128],
        "size": [16, 16],
        "scale": 4,
        "number_of_frames": 1,
        "dt_per_frame": -1
      },
      "blocking": true,
      "event_name": ""
    },
    {
      "sprite": {
        "name": "block-metal",
        "filename": "newlizardsprite.png",
        "location": [112, 128],
        "size": [16, 16],
        "scale": 4,
        "number_of_frames": 1,
        "dt_per_frame": -1
      },
      "blocking": true,
      "event_name": ""
    },
    {
      "sprite": {
        "name": "blocking-sheet",
        "filename": "newlizardsprite.png",
        "location": [128, 128],
        "size": [16, 16],
        "scale": 4,
        "number_of_frames": 1,
        "dt_per_frame": -1
      },
      "blocking": true,
      "event_name": ""
    },
    {
      "sprite": {
        "name": "metal-sheet",
        "filename": "newlizardsprite.png",
        "location": [128, 128],
        "size": [16, 16],
        "scale": 4,
        "number_of_frames": 1,
        "dt_per_frame": -1
      },
      "blocking": false,
      "event_name": ""
    },
    {
      "sprite": {
        "name": "water",
        "filename": "newlizardsprite.png",
        "location": [0, 160],
        "size": [16, 16],
        "scale": 4,
        "number_of_frames": 1,
        "dt_per_frame": -1
      },
      "blocking": false,
      "event_name": "in_water"
    }
  ]
}